mycalc/calculator.py
yejin230411-0.0.1.dist-info/METADATA
yejin230411-0.0.1.dist-info/WHEEL
yejin230411-0.0.1.dist-info/top_level.txt
yejin230411-0.0.1.dist-info/RECORD
